Blatt6/Gruppe20_Blatt6/6.2b/robot.vhdl
LIBRARY IEEE;
USE IEEE.Std_logic_1164.ALL;

ENTITY robot IS
    PORT (
        input_seq : IN STD_LOGIC_VECTOR := "1011"; -- Default value for input_seq is 1011 (ist die Sequenz die untersucht wird)
        Clk : IN STD_LOGIC;
        y : OUT BOOLEAN -- TRUE wenn 1011 in der Sequenz erkannt wird
    );
END robot;

ARCHITECTURE behavioral OF robot IS
BEGIN
    PROCESS (Clk, input_seq)
        VARIABLE counter : INTEGER := input_seq'length - 1;
        TYPE Zustaende IS (Z1, Z2, Z3, Z4);
        VARIABLE Zustand : Zustaende;
    BEGIN

        IF (rising_edge(Clk)) THEN -- fuer jede steigende Taktflanke wird ein Element der Eingabesequenz abgegangen
            IF (counter >= 0) THEN
                CASE Zustand IS
                    WHEN Z1 =>
                        IF input_seq(counter) = '1' THEN
                            Zustand := Z2;
                            y <= false;
                        ELSE
                            y <= false;
                        END IF;
                    WHEN Z2 =>
                        IF input_seq(counter) = '0' THEN
                            Zustand := Z3;
                            y <= false;
                        ELSE
                            y <= false; -- für 1 bleibt man im Zustand Z2
                        END IF;
                    WHEN Z3 =>
                        IF input_seq(counter) = '1' THEN
                            Zustand := Z4;
                            y <= false;
                        ELSE
                            Zustand := Z1;
                            y <= false;
                        END IF;
                    WHEN Z4 =>
                        IF input_seq(counter) = '1' THEN
                            Zustand := Z1;
                            y <= true;
                        ELSE
                            Zustand := Z3;
                            y <= false;
                        END IF;
                END CASE;
                counter := counter - 1;
            END IF;
        END IF;

    END PROCESS;
END behavioral;

Blatt6/Gruppe20_Blatt6/6.2b/robot_tb.vhdl
library ieee;
use ieee.std_logic_1164.all;

entity robot_tb is
end robot_tb;

architecture behavioral of robot_tb is
    component robot is
        port(
            input_seq : in std_logic_vector := "1011"; -- Default value for input_seq is 1011;
            Clk : in std_logic;
            y : out Boolean
        );
        end component;

        signal i : std_logic_vector(5 downto 0); -- Test an Sequenz der Länge 6
        signal Cl : std_logic;
        signal yo : boolean;

        begin
            r : robot port map(i, Cl, yo);

            process begin
                i <= "101101";
                Cl <= '0';
                wait for 10 ns;

                Cl <= '1';
                wait for 10 ns;
                
                Cl <= '0';
                wait for 10 ns;

                Cl <= '1';
                wait for 10 ns;
                Cl <= '0';
                wait for 10 ns;

                Cl <= '1';
                wait for 10 ns;
                Cl <= '0';
                wait for 10 ns;

                Cl <= '1';
                wait for 10 ns;
                Cl <= '0';
                wait for 10 ns;

                Cl <= '1';
                wait for 10 ns;
                Cl <= '0';
                wait for 10 ns;

                Cl <= '1';
                wait for 10 ns;
                wait;
                end process;
    end behavioral;

Blatt6/Gruppe20_Blatt6/6.2b/testbench.vcd
$date
  Wed May 25 21:50:01 2022
$end
$version
  GHDL v0
$end
$timescale
  1 fs
$end
$scope module standard $end
$upscope $end
$scope module std_logic_1164 $end
$upscope $end
$scope module robot_tb $end
$var reg 6 ! i[5:0] $end
$var reg 1 " cl $end
$var reg 1 # yo $end
$scope module r $end
$var reg 6 $ input_seq[5:0] $end
$var reg 1 % clk $end
$var reg 1 & y $end
$upscope $end
$upscope $end
$enddefinitions $end
#0
b101101 !
0"
0#
b101101 $
0%
0&
#10000000
1"
1%
#20000000
0"
0%
#30000000
1"
1%
#40000000
0"
0%
#50000000
1"
1%
#60000000
0"
0%
#70000000
1"
1#
1%
1&
#80000000
0"
0%
#90000000
1"
0#
1%
0&
#100000000
0"
0%
#110000000
1"
1%
