Blatt7/Gruppe20_Blatt7/7.1/parallel_mult.vhdl
LIBRARY ieee;
USE ieee.std_logic_1164.ALL;

--Three blocks are provided in this template(block_1, block_2 and block_3), 
--you can complete the design of this multiplier by connecting these blocks,
--or you can also design your own block based on your implementation.

ENTITY parallel_mult IS
	PORT (
		x, y : IN STD_LOGIC_VECTOR(3 DOWNTO 0);
		z : OUT STD_LOGIC_VECTOR(7 DOWNTO 0)
	);
END parallel_mult;

ARCHITECTURE rtl OF parallel_mult IS

	COMPONENT block_1
		PORT (
			andgate_in_1 : IN STD_LOGIC;
			andgate_in_2 : IN STD_LOGIC;
			andgate_out : OUT STD_LOGIC
		);
	END COMPONENT;

	COMPONENT block_2
		PORT (
			a, b, c, cin : IN STD_LOGIC;
			cout, sum : OUT STD_LOGIC
		);
	END COMPONENT;

	COMPONENT block_3
		PORT (
			a, b, c : IN STD_LOGIC;
			cout, sum : OUT STD_LOGIC
		);
	END COMPONENT;

	-- speichert die sout-Werten jeder Zeile
	SIGNAL z1, z2, z3, z4 : STD_LOGIC_VECTOR(3 DOWNTO 0);

	-- speichert die Uebertraeger jeder Zeile
	SIGNAL u2, u3, u4 : STD_LOGIC_VECTOR(3 DOWNTO 0);

BEGIN
	-- block_1 -> &-Gatter
	-- block_2 -> VA
	-- block_3 -> HA

	-- row 1 nur &-Gatter
	row_0_0 : block_1 PORT MAP(x(0), y(0), z1(0));
	row_0_1 : block_1 PORT MAP(x(1), y(0), z1(1));
	row_0_2 : block_1 PORT MAP(x(2), y(0), z1(2));
	row_0_3 : block_1 PORT MAP(x(3), y(0), z1(3));

	-- 		  block_3 PORT MAP(a   , b   , c    , cout , sum  );
	--   	  block_2 PORT MAP(a   , b   , c	, cin  , cout , sum  );
	-- b, c ~= x, y
	-- a = previous z
	-- row 2 bis 4: HA bei Index 0 und VA bei dem Rest 
	row_1_0 : block_3 PORT MAP(z1(1), x(0), y(1), u2(0), z2(0));
	row_1_1 : block_2 PORT MAP(z1(2), x(1), y(1), u2(0), u2(1), z2(1));
	row_1_2 : block_2 PORT MAP(z1(3), x(2), y(1), u2(1), u2(2), z2(2));
	row_1_3 : block_2 PORT MAP('0', x(3), y(1), u2(2), u2(3), z2(3));

	row_2_0 : block_3 PORT MAP(z2(1), x(0), y(2), u3(0), z3(0));
	row_2_1 : block_2 PORT MAP(z2(2), x(1), y(2), u3(0), u3(1), z3(1));
	row_2_2 : block_2 PORT MAP(z2(3), x(2), y(2), u3(1), u3(2), z3(2));
	row_2_3 : block_2 PORT MAP(u2(3), x(3), y(2), u3(2), u3(3), z3(3));

	row_3_0 : block_3 PORT MAP(z3(1), x(0), y(3), u4(0), z4(0));
	row_3_1 : block_2 PORT MAP(z3(2), x(1), y(3), u4(0), u4(1), z4(1));
	row_3_2 : block_2 PORT MAP(z3(3), x(2), y(3), u4(1), u4(2), z4(2));
	row_3_3 : block_2 PORT MAP(u3(3), x(3), y(3), u4(2), u4(3), z4(3));

	z(0) <= z1(0);
	z(1) <= z2(0);
	z(2) <= z3(0);
	z(3) <= z4(0);
	z(4) <= z4(1);
	z(5) <= z4(2);
	z(6) <= z4(3);
	z(7) <= u4(3);
END rtl;

--first block
LIBRARY ieee;
USE ieee.std_logic_1164.ALL;

ENTITY block_1 IS
	PORT (
		andgate_in_1 : IN STD_LOGIC;
		andgate_in_2 : IN STD_LOGIC;
		andgate_out : OUT STD_LOGIC
	);
END block_1;

ARCHITECTURE rtl OF block_1 IS
BEGIN
	andgate_out <= andgate_in_1 AND andgate_in_2;
END rtl;

--second block.
LIBRARY ieee;
USE ieee.std_logic_1164.ALL;

ENTITY block_2 IS
	PORT (
		a, b, c, cin : IN STD_LOGIC;
		cout, sum : OUT STD_LOGIC
	);
END block_2;

ARCHITECTURE rtl OF block_2 IS
	SIGNAL d : STD_LOGIC;
BEGIN
	d <= b AND c;
	cout <= (a AND d) OR (a AND cin) OR (d AND cin);
	sum <= a XOR d XOR cin;
END rtl;

--third block.
LIBRARY ieee;
USE ieee.std_logic_1164.ALL;

ENTITY block_3 IS
	PORT (
		a, b, c : IN STD_LOGIC;
		cout, sum : OUT STD_LOGIC
	);
END block_3;

ARCHITECTURE rtl OF block_3 IS
	SIGNAL d : STD_LOGIC;
BEGIN
	d <= b AND c;
	sum <= a XOR d;
	cout <= a AND d;
END rtl;

Blatt7/Gruppe20_Blatt7/7.1/parallel_mult_tb.vhdl
LIBRARY ieee;
USE ieee.std_logic_1164.ALL;

ENTITY parallel_mult_tb IS
END parallel_mult_tb;

ARCHITECTURE rtl OF parallel_mult_tb IS

	COMPONENT parallel_mult
		PORT (
			x, y : IN STD_LOGIC_VECTOR(3 DOWNTO 0);
			z : OUT STD_LOGIC_VECTOR(7 DOWNTO 0)
		);
	END COMPONENT;
	SIGNAL x, y : STD_LOGIC_VECTOR(3 DOWNTO 0);
	SIGNAL z : STD_LOGIC_VECTOR(7 DOWNTO 0);
BEGIN
	parallel_mult_1 : parallel_mult PORT MAP(x => x, y => y, z => z);
	PROCESS BEGIN
		x <= "1010";
		y <= "1101";
		WAIT FOR 10 ns;

		y <= "0111";
		WAIT FOR 10 ns;

		x <= "1001";
		y <= "1101";
		WAIT FOR 10 ns;

		y <= "0111";
		WAIT FOR 10 ns;

		-- weitere Testergebnisse
		x <= "1111";
		y <= "0000"; -- 15 * 0
		WAIT FOR 10 ns;

		x <= "1111";
		y <= "1111"; -- 15 * 15
		WAIT FOR 10 ns;

		x <= "0001";
		y <= "1001"; -- 1 * 9
		WAIT FOR 10 ns;

		x <= "1100";
		y <= "0100"; -- 12 * 8
		WAIT FOR 10 ns;

		WAIT;
	END PROCESS;
END rtl;

Blatt7/Gruppe20_Blatt7/7.1/testbench.vcd
$date
  Wed Jun 01 21:50:35 2022
$end
$version
  GHDL v0
$end
$timescale
  1 fs
$end
$scope module standard $end
$upscope $end
$scope module std_logic_1164 $end
$upscope $end
$scope module parallel_mult_tb $end
$var reg 4 ! x[3:0] $end
$var reg 4 " y[3:0] $end
$var reg 8 # z[7:0] $end
$scope module parallel_mult_1 $end
$var reg 4 $ x[3:0] $end
$var reg 4 % y[3:0] $end
$var reg 8 & z[7:0] $end
$var reg 4 ' z1[3:0] $end
$var reg 4 ( z2[3:0] $end
$var reg 4 ) z3[3:0] $end
$var reg 4 * z4[3:0] $end
$var reg 4 + u2[3:0] $end
$var reg 4 , u3[3:0] $end
$var reg 4 - u4[3:0] $end
$scope module row_0_0 $end
$var reg 1 . andgate_in_1 $end
$var reg 1 / andgate_in_2 $end
$var reg 1 0 andgate_out $end
$upscope $end
$scope module row_0_1 $end
$var reg 1 1 andgate_in_1 $end
$var reg 1 2 andgate_in_2 $end
$var reg 1 3 andgate_out $end
$upscope $end
$scope module row_0_2 $end
$var reg 1 4 andgate_in_1 $end
$var reg 1 5 andgate_in_2 $end
$var reg 1 6 andgate_out $end
$upscope $end
$scope module row_0_3 $end
$var reg 1 7 andgate_in_1 $end
$var reg 1 8 andgate_in_2 $end
$var reg 1 9 andgate_out $end
$upscope $end
$scope module row_1_0 $end
$var reg 1 : a $end
$var reg 1 ; b $end
$var reg 1 < c $end
$var reg 1 = cout $end
$var reg 1 > sum $end
$var reg 1 ? d $end
$upscope $end
$scope module row_1_1 $end
$var reg 1 @ a $end
$var reg 1 A b $end
$var reg 1 B c $end
$var reg 1 C cin $end
$var reg 1 D cout $end
$var reg 1 E sum $end
$var reg 1 F d $end
$upscope $end
$scope module row_1_2 $end
$var reg 1 G a $end
$var reg 1 H b $end
$var reg 1 I c $end
$var reg 1 J cin $end
$var reg 1 K cout $end
$var reg 1 L sum $end
$var reg 1 M d $end
$upscope $end
$scope module row_1_3 $end
$var reg 1 N a $end
$var reg 1 O b $end
$var reg 1 P c $end
$var reg 1 Q cin $end
$var reg 1 R cout $end
$var reg 1 S sum $end
$var reg 1 T d $end
$upscope $end
$scope module row_2_0 $end
$var reg 1 U a $end
$var reg 1 V b $end
$var reg 1 W c $end
$var reg 1 X cout $end
$var reg 1 Y sum $end
$var reg 1 Z d $end
$upscope $end
$scope module row_2_1 $end
$var reg 1 [ a $end
$var reg 1 \ b $end
$var reg 1 ] c $end
$var reg 1 ^ cin $end
$var reg 1 _ cout $end
$var reg 1 ` sum $end
$var reg 1 a d $end
$upscope $end
$scope module row_2_2 $end
$var reg 1 b a $end
$var reg 1 c b $end
$var reg 1 d c $end
$var reg 1 e cin $end
$var reg 1 f cout $end
$var reg 1 g sum $end
$var reg 1 h d $end
$upscope $end
$scope module row_2_3 $end
$var reg 1 i a $end
$var reg 1 j b $end
$var reg 1 k c $end
$var reg 1 l cin $end
$var reg 1 m cout $end
$var reg 1 n sum $end
$var reg 1 o d $end
$upscope $end
$scope module row_3_0 $end
$var reg 1 p a $end
$var reg 1 q b $end
$var reg 1 r c $end
$var reg 1 s cout $end
$var reg 1 t sum $end
$var reg 1 u d $end
$upscope $end
$scope module row_3_1 $end
$var reg 1 v a $end
$var reg 1 w b $end
$var reg 1 x c $end
$var reg 1 y cin $end
$var reg 1 z cout $end
$var reg 1 { sum $end
$var reg 1 | d $end
$upscope $end
$scope module row_3_2 $end
$var reg 1 } a $end
$var reg 1 !" b $end
$var reg 1 "" c $end
$var reg 1 #" cin $end
$var reg 1 $" cout $end
$var reg 1 %" sum $end
$var reg 1 &" d $end
$upscope $end
$scope module row_3_3 $end
$var reg 1 '" a $end
$var reg 1 (" b $end
$var reg 1 )" c $end
$var reg 1 *" cin $end
$var reg 1 +" cout $end
$var reg 1 ," sum $end
$var reg 1 -" d $end
$upscope $end
$upscope $end
$upscope $end
$enddefinitions $end
#0
b1010 !
b1101 "
b10000010 #
b1010 $
b1101 %
b10000010 &
b1010 '
b0101 (
b1100 )
b0000 *
b0000 +
b0010 ,
b1110 -
0.
1/
00
11
12
13
04
15
06
17
18
19
1:
0;
0<
0=
1>
0?
0@
1A
0B
0C
0D
0E
0F
1G
0H
0I
0J
0K
1L
0M
0N
1O
0P
0Q
0R
0S
0T
0U
0V
1W
0X
0Y
0Z
1[
1\
1]
0^
1_
0`
1a
0b
0c
1d
1e
0f
1g
0h
0i
1j
1k
0l
0m
1n
1o
0p
0q
1r
0s
0t
0u
1v
1w
1x
0y
1z
0{
1|
1}
0!"
1""
1#"
1$"
0%"
0&"
0'"
1("
1)"
1*"
1+"
0,"
1-"
#10000000
b0111 "
b01000110 #
b0111 %
b01000110 &
b1111 (
b0001 )
b1000 *
b1110 ,
b0000 -
1<
1B
1E
1F
1I
1P
1S
1T
1U
1Y
1b
1f
0g
1l
1m
0n
0r
0v
0x
0z
0{
0|
0}
0""
0#"
0$"
0%"
1'"
0)"
0*"
0+"
1,"
0-"
#20000000
b1001 !
b1101 "
b01110101 #
b1001 $
b1101 %
b01110101 &
b1001 '
b0100 (
b1011 )
b1110 *
b0000 ,
b0001 -
1.
10
01
03
0:
1;
0<
0>
0A
0B
0E
0F
0I
0P
0S
0T
0U
1V
0X
1Y
1Z
0\
0^
0_
1`
0a
0b
0e
0f
0g
0l
0m
1n
1p
1q
1r
1s
0t
1u
0v
0w
1x
1y
1{
1}
1""
1%"
0'"
1)"
0+"
1,"
1-"
#30000000
b0111 "
b00111111 #
b0111 %
b00111111 &
b1101 (
b1111 )
b0111 *
b0000 -
1<
1>
1?
1B
1I
1P
1S
1T
1b
1g
0r
0s
1t
0u
1v
0x
0y
1{
0""
0)"
0,"
0-"
#40000000
b1111 !
b0000 "
b00000000 #
b1111 $
b0000 %
b00000000 &
b0000 '
b0000 (
b0000 )
b0000 *
0/
00
11
02
14
05
08
09
0<
0>
0?
1A
0B
0G
1H
0I
0L
0P
0S
0T
0W
0Y
0Z
0[
1\
0]
0`
0b
1c
0d
0g
0k
0n
0o
0p
0t
0v
1w
0{
0}
1!"
0%"
#50000000
b1111 "
b11100001 #
b1111 %
b11100001 &
b1111 '
b0110 (
b1010 )
b1100 *
b1111 +
b1111 ,
b1111 -
1/
10
12
13
15
16
18
19
1:
1<
1=
1?
1@
1B
1C
1D
1E
1F
1G
1I
1J
1K
1L
1M
1P
1Q
1R
0S
1T
1U
1W
1X
0Y
1Z
1[
1]
1^
1_
1`
1a
0b
1d
1e
1f
0g
1h
1i
1k
1l
1m
1n
1o
1p
1r
1s
0t
1u
0v
1x
1y
1z
0{
1|
1}
1""
1#"
1$"
1%"
1&"
1'"
1)"
1*"
1+"
1,"
1-"
#60000000
b0001 !
b1001 "
b00001001 #
b0001 $
b1001 %
b00001001 &
b0001 '
b0000 (
b0000 )
b0001 *
b0000 +
b0000 ,
b0000 -
01
03
04
06
07
09
0:
0<
0=
0?
0@
0A
0B
0C
0D
0E
0F
0G
0H
0I
0J
0K
0L
0M
0O
0P
0Q
0R
0S
0T
0U
0W
0X
0Y
0Z
0[
0\
0]
0^
0_
0`
0a
0b
0c
0d
0e
0f
0g
0h
0i
0j
0k
0l
0m
0n
0o
0p
0s
1t
0v
0w
0y
0z
0{
0|
0}
0!"
0#"
0$"
0%"
0&"
0'"
0("
0*"
0+"
0,"
0-"
#70000000
b1100 !
b0100 "
b00110000 #
b1100 $
b0100 %
b00110000 &
b0000 '
b1100 )
b0110 *
0.
0/
00
02
14
05
17
08
0;
1H
1O
0V
1W
1]
1c
1d
1g
1h
1j
1k
1n
1o
0q
0r
0t
0u
1v
0x
1{
1}
1!"
0""
1%"
1("
0)"
