Blatt6/Gruppe20_Blatt6/6.3/jk_flipflop.vhdl
library ieee;
use ieee.std_logic_1164.all;

entity jk_flipflop is
    port(
        j,k, clk, reset : in std_logic;
        Q : out std_logic
    );
end jk_flipflop;

architecture bh of jk_flipflop is
        signal q_int : std_logic;
    begin
        q <= q_int;
        process begin
            wait until rising_edge(clk);
                if (reset = '1') then
                    q_int <= '0';
                elsif (j = '0' and k = '1') then
                    q_int <= '0';
                elsif (j = '1' and k = '0') then
                    q_int <= '1';
                elsif (j = '1' and k = '1') then
                    q_int <= not q_int;
                end if;
        end process;
end bh;

Blatt1/blatt01/Blatt5/Gruppe018_Abgabe05/blatt05/5.3/jk_ff_tb.vhdl
library ieee;
use ieee.std_logic_1164.all;

entity jk_ff_tb is
end jk_ff_tb;

architecture testbench of jk_ff_tb is

component JK_FlipFlop is
    port (
      J,K, clk , reset : in std_logic;
      Q : out std_logic
    );
end component;

signal j, k, c, r, q : std_logic;

begin

jkff : JK_FlipFlop port map (j, k, c, r, q);

process begin

    r <= '1';
    c <= '0';
    j <= '0';
    k <= '0';
    wait for 10 ns;
    j <= '1';
    k <= '0';
    wait for 10 ns;
    j <= '0';
    k <= '1';
    wait for 10 ns;
    j <= '1';
    k <= '1';
    wait for 10 ns;

    c <= '1';
    j <= '0';
    k <= '0';
    wait for 10 ns;
    j <= '1';
    k <= '0';
    wait for 10 ns;
    j <= '0';
    k <= '1';
    wait for 10 ns;
    j <= '1';
    k <= '1';
    wait for 10 ns;

    r <= '0';
    c <= '0';
    j <= '0';
    k <= '0';
    wait for 10 ns;
    j <= '1';
    k <= '0';
    wait for 10 ns;
    j <= '0';
    k <= '1';
    wait for 10 ns;
    j <= '1';
    k <= '1';
    wait for 10 ns;

    c <= '1';
    j <= '0';
    k <= '0';
    wait for 10 ns;
    j <= '1';
    k <= '0';
    wait for 10 ns;
    j <= '0';
    k <= '1';
    wait for 10 ns;
    j <= '1';
    k <= '1';
    wait for 10 ns;

	wait;
end process;

end testbench;

Blatt1/blatt01/Blatt5/Gruppe018_Abgabe05/blatt05/5.3/testbench.vcd
$date
  Thu May 18 18:53:57 2023
$end
$version
  GHDL v0
$end
$timescale
  1 fs
$end
$scope module standard $end
$upscope $end
$scope module std_logic_1164 $end
$upscope $end
$scope module jk_ff_tb $end
$var reg 1 ! j $end
$var reg 1 " k $end
$var reg 1 # c $end
$var reg 1 $ r $end
$var reg 1 % q $end
$scope module jkff $end
$var reg 1 & j $end
$var reg 1 ' k $end
$var reg 1 ( clk $end
$var reg 1 ) reset $end
$var reg 1 * q $end
$var reg 1 + q_int $end
$upscope $end
$upscope $end
$enddefinitions $end
#0
0!
0"
0#
1$
U%
0&
0'
0(
1)
U*
U+
#10000000
1!
1&
#20000000
0!
1"
0&
1'
#30000000
1!
1&
#40000000
0!
0"
1#
0%
0&
0'
1(
0*
0+
#50000000
1!
1&
#60000000
0!
1"
0&
1'
#70000000
1!
1&
#80000000
0!
0"
0#
0$
0&
0'
0(
0)
#90000000
1!
1&
#100000000
0!
1"
0&
1'
#110000000
1!
1&
#120000000
0!
0"
1#
0&
0'
1(
#130000000
1!
1&
#140000000
0!
1"
0&
1'
#150000000
1!
1&
