blatt02/2.3b_gatter/norgate/norgate.vhdl
library ieee;
use ieee.std_logic_1164.all;

entity norgate is
  port(
   input1:in std_logic;
   input2:in std_logic;
   nor_result:out std_logic
   );
end norgate;

architecture rtl of norgate is
  signal nor_gate:std_logic;
begin
  nor_gate<=input1 nor input2;
  nor_result<=nor_gate;
end rtl;

Blatt1/blatt01/Blatt5/Gruppe018_Abgabe05/blatt05/5.1/SR_Latch.vhdl
library ieee;
use ieee.std_logic_1164.all;

entity SR_Latch is
    port (
      S,R : in std_logic;
      Q,not_Q : out std_logic
    );
  end SR_Latch;

architecture Behavioral of SR_Latch is
    COMPONENT norgate IS
    PORT (
      input1 : IN STD_LOGIC;
      input2 : IN STD_LOGIC;
      nor_result : OUT STD_LOGIC
    );
    END COMPONENT;
	-- wir brauchen 2 andere Signale, die diesen Ausgabewert als Eingabewert des anderen Gatters speichern, da Q und not_Q nicht unmittelbar gelesen werden können
    SIGNAL q1, q2 : STD_LOGIC;
    -- q1 ~ Q, q2 ~ not_Q

begin
    -- erste nor Gatter mit S als Input
   snor : norgate PORT MAP(S, q1, q2);
   -- zweite nor Gatter mit R als Input
   rnor : norgate PORT MAP(R, q2, q1);
   -- dann speichern wir temporal die Variablen im Output
   Q <= q1;
   not_Q <= q2;

end Behavioral;

Blatt5/Gruppe018_Abgabe05/blatt05/5.2/andgate.vhdl
-- from the ieee libary we use std_logic_1164
-- defines a standard for logic values used in electronic design
-- for more info check the std_logic_1164.vhdl file in ghdl/libraries/ieee
-- ieee libary also defines operators and keywords

-- wir verwenden std_logic_1164 aus der IEEE libary
-- diese Datei definiert die Standards fuer logische Werte im elektronischen Design
-- Details finden sich in der Datei std_logic_1164.vhdl in ghdl/libraries/ieee
-- Die IEEE libary definiert auch operatoren und Schluesselwoerter
library ieee;
use ieee.std_logic_1164.all;

-- entities defined in a file (notgate.vhdl) are can be seen as black boxes
-- entities have ports that defines all inputs and outputs 
-- std_logic can have 9 different values, it is part of std_logic_1164 package
-- you can think of it as a single bit

-- die in einer Datei definierten entities koennen als black box angesehen werden. 
-- entities haben ports die Eingaben und Ausgaben definieren
-- std_logic kann 9 unterschiedliche Werte annehmen (siehe Aufgabe 2.1)
-- kann als einzelnes bit verstanden werden
entity andgate is
  -- the andgate as two in ports named "input1" and "input2", and one out port named "and_result"
  -- das andgate hat zwei Eingangsports "input1" und "input2" sowie einen Ausgangsport "and_result"
  port (
    input1 : in std_logic;
    input2 : in std_logic;
    and_result : out std_logic
  );
end andgate;

-- architecture describes functionality of particular entity
-- like the implementation of a function
-- actually describes the "internal wiring" of block
-- interconnection signals, constants, or other components

-- die Architekture beschreibt die Funktionalitaet einer entity
-- aehnlich wie die Implementierung einer Funktion
-- beschreibt die "innere Verdrahtung" eines blocks
-- verbindet Signale, Konstanten oder andere Komponenten
architecture rtl of andgate is
  -- internal signal, not yet connected to the outside
  -- internes Signal, bisher nicht nach aussen verbunden
  signal and_gate : std_logic;
begin
  -- setting the internal signal, based on the desired logical functionality (here: logical and of the two input values)
  -- internes Signal wird entsprechend der benoetigten Funktionalitaet gesetzt (hier: logisches und der Eingabewerte)
  and_gate <= input1 and input2;
  -- internal signal gets connected to the outside
  -- internes Signal wird nach aussen verbunden
  and_result <= and_gate;
end rtl;

Blatt5/Gruppe018_Abgabe05/blatt05/5.1/D_Latch.vhdl
library ieee;
use ieee.std_logic_1164.all;

entity D_Latch is
    port(
        D, clk : in std_logic;
        Q, not_Q : out std_logic
    );
end D_Latch;

architecture Behavioral of D_Latch is
    COMPONENT SR_latch IS
        PORT (
            S, R : IN STD_LOGIC;
            Q, not_Q : OUT STD_LOGIC
        );
    END COMPONENT;

    COMPONENT andgate IS
        PORT (
            input1, input2 : IN STD_LOGIC;
            and_result : OUT STD_LOGIC
        );
    END COMPONENT;
    -- Negierter Wert von d speichern
    SIGNAL notd : STD_LOGIC;
    -- Zugewiesene Werte in R und S speichern
    SIGNAL r, s : STD_LOGIC;

begin
    notd <= NOT D;
    -- and-Gatter für den Eingang R
    andr : andgate PORT MAP(clk, notd, r);
    -- and-Gatter für den Eingang S
    ands : andgate PORT MAP(clk, D, s);
    -- SR-Latch
    sr : SR_latch PORT MAP(s, r, Q, not_Q);
end Behavioral;

Blatt5/Gruppe018_Abgabe05/blatt05/5.2/ms_ff.vhdl
library ieee;
use ieee.std_logic_1164.all;

entity ms_ff is
    port (
      d, clk: in std_logic;
      Q, not_Q : out std_logic
    );
  end ms_ff;

architecture behavioral of ms_ff is
    COMPONENT D_Latch IS
    PORT (
      D, clk : IN STD_LOGIC;
      Q, not_Q : OUT STD_LOGIC
    );
    END COMPONENT;

    -- invertiert clk
    SIGNAL notclk : STD_LOGIC;
    -- n1 Mittelsignal
    SIGNAL n1 : STD_LOGIC;
    -- Füllsignale (master!Q brauchen wir nicht)
    SIGNAL nqm : STD_LOGIC;

begin
    notclk <= NOT clk;
    -- n1 = masterQ
    master : D_Latch PORT MAP(d, notclk, n1, nqm);
    slave : D_Latch PORT MAP(n1, clk, Q, not_Q);

end behavioral ;

Blatt5/Gruppe018_Abgabe05/blatt05/5.2/ms_ff_tb.vhdl
library ieee;
use ieee.std_logic_1164.all;

entity ms_ff_tb is
end ms_ff_tb;

architecture testbench of ms_ff_tb is
    COMPONENT ms_ff IS
        PORT (
            d, clk : IN STD_LOGIC;
            Q, not_Q : OUT STD_LOGIC
        );
    END COMPONENT;

    SIGNAL d, clk, q, nq : STD_LOGIC;

begin
    msdff : ms_ff PORT MAP(d, clk, q, nq);

    -- (fast) genau wie Abb. 4
    PROCESS BEGIN
        clk <= '0';
        d <= '0';
        WAIT FOR 10 ns; -- 10ns + Fall 00
        -- Q ist undefiniert für den ersten 10ns, da wir noch kein Qprev haben.
        clk <= '1';
        WAIT FOR 10 ns; -- 20ns
        clk <= '0';
        WAIT FOR 2.5 ns; -- 22.5ns
        d <= '1';
        WAIT FOR 2.5 ns; -- 25ns + Fall 01
        d <= '0';
        WAIT FOR 2.5 ns; -- 27.5ns
        d <= '1';
        WAIT FOR 2.5 ns; -- 30ns
        clk <= '1';
        WAIT FOR 2.5 ns; -- 32.5ns + Fall 11
        d <= '0';
        WAIT FOR 2.5 ns; -- 35ns + Fall 10
        WAIT FOR 5 ns; -- 40ns 
        clk <= '0';
        WAIT FOR 10 ns; -- 50ns
        clk <= '1';
        WAIT FOR 10 ns; -- 60ns
        clk <= '0';
        -- endet hier bei 60ns, es wird zu kompliziert für die genaue Signal wie im Abb.
        WAIT;
    END PROCESS;
   
end testbench;

Blatt5/Gruppe018_Abgabe05/blatt05/5.2/testbench.vcd
$date
  Thu May 18 18:22:38 2023
$end
$version
  GHDL v0
$end
$timescale
  1 fs
$end
$scope module standard $end
$upscope $end
$scope module std_logic_1164 $end
$upscope $end
$scope module ms_ff_tb $end
$var reg 1 ! d $end
$var reg 1 " clk $end
$var reg 1 # q $end
$var reg 1 $ nq $end
$scope module msdff $end
$var reg 1 % d $end
$var reg 1 & clk $end
$var reg 1 ' q $end
$var reg 1 ( not_q $end
$var reg 1 ) notclk $end
$var reg 1 * n1 $end
$var reg 1 + nqm $end
$scope module master $end
$var reg 1 , d $end
$var reg 1 - clk $end
$var reg 1 . q $end
$var reg 1 / not_q $end
$var reg 1 0 notd $end
$var reg 1 1 r $end
$var reg 1 2 s $end
$scope module andr $end
$var reg 1 3 input1 $end
$var reg 1 4 input2 $end
$var reg 1 5 and_result $end
$var reg 1 6 and_gate $end
$upscope $end
$scope module ands $end
$var reg 1 7 input1 $end
$var reg 1 8 input2 $end
$var reg 1 9 and_result $end
$var reg 1 : and_gate $end
$upscope $end
$scope module sr $end
$var reg 1 ; s $end
$var reg 1 < r $end
$var reg 1 = q $end
$var reg 1 > not_q $end
$var reg 1 ? q1 $end
$var reg 1 @ q2 $end
$scope module snor $end
$var reg 1 A input1 $end
$var reg 1 B input2 $end
$var reg 1 C nor_result $end
$var reg 1 D nor_gate $end
$upscope $end
$scope module rnor $end
$var reg 1 E input1 $end
$var reg 1 F input2 $end
$var reg 1 G nor_result $end
$var reg 1 H nor_gate $end
$upscope $end
$upscope $end
$upscope $end
$scope module slave $end
$var reg 1 I d $end
$var reg 1 J clk $end
$var reg 1 K q $end
$var reg 1 L not_q $end
$var reg 1 M notd $end
$var reg 1 N r $end
$var reg 1 O s $end
$scope module andr $end
$var reg 1 P input1 $end
$var reg 1 Q input2 $end
$var reg 1 R and_result $end
$var reg 1 S and_gate $end
$upscope $end
$scope module ands $end
$var reg 1 T input1 $end
$var reg 1 U input2 $end
$var reg 1 V and_result $end
$var reg 1 W and_gate $end
$upscope $end
$scope module sr $end
$var reg 1 X s $end
$var reg 1 Y r $end
$var reg 1 Z q $end
$var reg 1 [ not_q $end
$var reg 1 \ q1 $end
$var reg 1 ] q2 $end
$scope module snor $end
$var reg 1 ^ input1 $end
$var reg 1 _ input2 $end
$var reg 1 ` nor_result $end
$var reg 1 a nor_gate $end
$upscope $end
$scope module rnor $end
$var reg 1 b input1 $end
$var reg 1 c input2 $end
$var reg 1 d nor_result $end
$var reg 1 e nor_gate $end
$upscope $end
$upscope $end
$upscope $end
$upscope $end
$upscope $end
$enddefinitions $end
#0
0!
0"
U#
U$
0%
0&
U'
U(
1)
0*
1+
0,
1-
0.
1/
10
11
02
13
14
15
16
17
08
09
0:
0;
1<
0=
1>
0?
1@
0A
0B
1C
1D
1E
1F
0G
0H
0I
0J
UK
UL
1M
0N
0O
0P
1Q
0R
0S
0T
0U
0V
0W
0X
0Y
UZ
U[
U\
U]
0^
U_
U`
Ua
0b
Uc
Ud
Ue
#10000000
1"
0#
1$
1&
0'
1(
0)
0-
01
03
05
06
07
0<
0E
1J
0K
1L
1N
1P
1R
1S
1T
1Y
0Z
1[
0\
1]
0_
1`
1a
1b
1c
0d
0e
#20000000
0"
0&
1)
1-
11
13
15
16
17
1<
1E
0J
0N
0P
0R
0S
0T
0Y
0b
#22500000
1!
1%
1*
0+
1,
1.
0/
00
01
12
04
05
06
18
19
1:
1;
0<
1=
0>
1?
0@
1A
1B
0C
0D
0E
0F
1G
1H
1I
0M
0Q
1U
#25000000
0!
0%
0*
1+
0,
0.
1/
10
11
02
14
15
16
08
09
0:
0;
1<
0=
1>
0?
1@
0A
0B
1C
1D
1E
1F
0G
0H
0I
1M
1Q
0U
#27500000
1!
1%
1*
0+
1,
1.
0/
00
01
12
04
05
06
18
19
1:
1;
0<
1=
0>
1?
0@
1A
1B
0C
0D
0E
0F
1G
1H
1I
0M
0Q
1U
#30000000
1"
1#
0$
1&
1'
0(
0)
0-
02
03
07
09
0:
0;
0A
1J
1K
0L
1O
1P
1T
1V
1W
1X
1Z
0[
1\
0]
1^
1_
0`
0a
0c
1d
1e
#32500000
0!
0%
0,
10
14
08
#35000000
#40000000
0"
0&
1)
0*
1+
1-
0.
1/
11
13
15
16
17
1<
0=
1>
0?
1@
0B
1C
1D
1E
1F
0G
0H
0I
0J
1M
0O
0P
1Q
0T
0U
0V
0W
0X
0^
#50000000
1"
0#
1$
1&
0'
1(
0)
0-
01
03
05
06
07
0<
0E
1J
0K
1L
1N
1P
1R
1S
1T
1Y
0Z
1[
0\
1]
0_
1`
1a
1b
1c
0d
0e
#60000000
0"
0&
1)
1-
11
13
15
16
17
1<
1E
0J
0N
0P
0R
0S
0T
0Y
0b
